[
    {
        "name": "Andrea Vance"
    },
    {
        "name": "Knight Carey"
    },
    {
        "name": "Henson Ferguson"
    },
    {
        "name": "Cline Witt"
    },
    {
        "name": "June Mcgee"
    },
    {
        "name": "Booth Thornton"
    },
    {
        "name": "Shelton Porter"
    },
    {
        "name": "Ivy Ortiz"
    },
    {
        "name": "Ford Reilly"
    },
    {
        "name": "Jacobson Patel"
    },
    {
        "name": "Rosario Robles"
    },
    {
        "name": "Best Swanson"
    },
    {
        "name": "Schroeder Ingram"
    },
    {
        "name": "Bonnie Wynn"
    },
    {
        "name": "Barry Hammond"
    },
    {
        "name": "Julianne Sykes"
    },
    {
        "name": "Lorrie Evans"
    },
    {
        "name": "Anderson Berger"
    },
    {
        "name": "Quinn Jacobson"
    },
    {
        "name": "Reynolds Abbott"
    },
    {
        "name": "Brooke Lucas"
    },
    {
        "name": "Kathryn Palmer"
    },
    {
        "name": "Oliver Nash"
    },
    {
        "name": "Louisa Orr"
    },
    {
        "name": "Mcgowan Price"
    },
    {
        "name": "Hendrix Salinas"
    },
    {
        "name": "Annie Contreras"
    },
    {
        "name": "Sonja Faulkner"
    },
    {
        "name": "Angie Bennett"
    },
    {
        "name": "Beasley Bird"
    }
]
